uniquant/__init__.py
uniquant/Platforms/__init__.py
uniquant/Platforms/Binance/Public.py
uniquant/Platforms/Binance/Public.pyi
uniquant/Platforms/Binance/__init__.py
uniquant/main/__exceptions__.py
uniquant/main/__init__.py
uniquant/main/logger.py
uniquant/main/platform.py
uniquant/main/utils.py
uniquant/main/vars.py
uniquant-1.0.3.dist-info/licenses/LICENSE
uniquant-1.0.3.dist-info/METADATA
uniquant-1.0.3.dist-info/WHEEL
uniquant-1.0.3.dist-info/top_level.txt
uniquant-1.0.3.dist-info/RECORD
