Metadata-Version: 2.4
Name: uniquant
Version: 1.0.3
Summary: An open-source asynchronous Python library for standardized access to cryptocurrency exchange market data APIs.
Author-email: Broo-Dev-X <broodevx@gmail.com>
License: MIT License
Project-URL: Homepage, https://github.com/Broo-DevX-Coder/Uniquant
Project-URL: Documentation, https://github.com/Broo-DevX-Coder/Uniquant/wiki
Project-URL: Issues, https://github.com/Broo-DevX-Coder/Uniquant/issues
Requires-Python: >=3.9
License-File: LICENSE
Requires-Dist: aiohttp>=3.8.0
Requires-Dist: websockets>=10.0
Dynamic: license-file
